[{
    "author": {
        "username": "Sam"
    },
    "timeStamp": "2024-10-01 10:23:00",
    "id": "1",
    "chatMessage": "Hello bro, this is Sam. How are you doing?",
    "imageUrl": "assets/images/image.png"

},{
    "author": {
        "username": "Kweku"
    },
    "timeStamp": "2024-10-01 10:23:00",
    "id": "1",
    "chatMessage": "Hello bro"
},{
    "author": {
        "username": "Kweku"
    },
    "timeStamp": "2024-10-01 10:23:00",
    "id": "1",
    "chatMessage": "I'm good and you?",
    "imageUrl": "assets/images/image.png"
},{
    "author": {
        "username": "Sam"
    },
    "timeStamp": "2024-10-01 10:23:00",
    "id": "1",
    "chatMessage": "I'm good too, thanks",
    "imageUrl": "assets/images/image.png"
}]